<?xml version="1.0" encoding="UTF-8"?>
<objects serializationModel="Studio.02.02.00">
	<object class="AudioFile" id="{9ad2e79b-d25b-4fa9-a386-8048223218af}">
		<property name="assetPath">
			<value>SFX/Whisper Sound Effect _ Whispering Gossip Sound Effects _ Various Sounds Of Small Group Whispering.1whisper loud.wav</value>
		</property>
		<property name="isStreaming">
			<value>true</value>
		</property>
		<property name="frequencyInKHz">
			<value>44.0999985</value>
		</property>
		<property name="channelCount">
			<value>2</value>
		</property>
		<property name="length">
			<value>35.322585034013606</value>
		</property>
		<relationship name="masterAssetFolder">
			<destination>{188bf2d1-af14-438a-8d41-9e3c00350b40}</destination>
		</relationship>
	</object>
</objects>
